examples/__init__.py
examples/database_example.py
examples/mnist.py
examples/model_selection.py
examples/model_selection_database.py
examples/nonlinear_regression.py
examples/nonlinear_regression_utils.py
fireworks/__init__.py
fireworks/core/__init__.py
fireworks/core/cache.py
fireworks/core/cache_test.py
fireworks/core/component_map.py
fireworks/core/component_map_test.py
fireworks/core/junction.py
fireworks/core/junction_test.py
fireworks/core/message.py
fireworks/core/message_test.py
fireworks/core/model.py
fireworks/core/model_test.py
fireworks/core/pipe.py
fireworks/core/pipe_test.py
fireworks/core/scaffold.py
fireworks/core/scaffold_test.py
fireworks/extensions/__init__.py
fireworks/extensions/database.py
fireworks/extensions/database_test.py
fireworks/extensions/experiment.py
fireworks/extensions/experiment_test.py
fireworks/extensions/explain.py
fireworks/extensions/explain_test.py
fireworks/extensions/factory.py
fireworks/extensions/factory_test.py
fireworks/extensions/training.py
fireworks/extensions/training_test.py
fireworks/toolbox/__init__.py
fireworks/toolbox/junctions.py
fireworks/toolbox/junctions_test.py
fireworks/toolbox/pipes.py
fireworks/toolbox/pipes_test.py
fireworks/toolbox/preprocessing.py
fireworks/toolbox/preprocessing_test.py
fireworks/toolbox/text.py
fireworks/toolbox/text_test.py
fireworks/utils/__init__.py
fireworks/utils/events.py
fireworks/utils/exceptions.py
fireworks/utils/test_helpers.py
fireworks/utils/utils.py
fireworks/utils/utils_test.py
fireworks_ml-0.3.9.dist-info/LICENSE
fireworks_ml-0.3.9.dist-info/METADATA
fireworks_ml-0.3.9.dist-info/WHEEL
fireworks_ml-0.3.9.dist-info/top_level.txt
fireworks_ml-0.3.9.dist-info/RECORD
