Metadata-Version: 2.1
Name: fireworks-ml
Version: 0.3.9
Summary: A batch-processing framework for data analysis and machine learning using PyTorch.
Home-page: https://github.com/smk508/fireworks
Author: UNKNOWN
Author-email: skhan8@mail.einstein.yu.edu
License: UNKNOWN
Platform: UNKNOWN
Classifier: Programming Language :: Python :: 3
Classifier: License :: OSI Approved :: MIT License
Classifier: Operating System :: OS Independent
Requires-Dist: bidict (>=0.18.0)
Requires-Dist: biopython (>==1.73)
Requires-Dist: Deprecated (>=1.2.5)
Requires-Dist: numpy (>=1.16.4)
Requires-Dist: pandas (>=0.24.2)
Requires-Dist: matplotlib (>=3.0.3)
Requires-Dist: pyarrow (>=0.14.1)
Requires-Dist: python-dateutil (>=2.8.0)
Requires-Dist: pytorch-ignite (>=0.2.0)
Requires-Dist: six (>=1.12.0)
Requires-Dist: SQLAlchemy (>=1.3.4)
Requires-Dist: SQLAlchemy-Utils (>0.33.5)
Requires-Dist: torch (>=1.1.0)
Requires-Dist: torchvision (>=0.3.0)
Requires-Dist: torchfile (>=0.1.0)
Requires-Dist: wrapt (>=1.11.1)
Requires-Dist: visdom (>=0.1.8.4)
